polarcodes/AWGN.py
polarcodes/Construct.py
polarcodes/Decode.py
polarcodes/Encode.py
polarcodes/GUI.py
polarcodes/PolarCode.py
polarcodes/Puncture.py
polarcodes/SCD.py
polarcodes/Shorten.py
polarcodes/__init__.py
polarcodes/decoder_utils.py
polarcodes/utils.py
py_polar_codes-1.2.1.dist-info/LICENSE
py_polar_codes-1.2.1.dist-info/METADATA
py_polar_codes-1.2.1.dist-info/WHEEL
py_polar_codes-1.2.1.dist-info/top_level.txt
py_polar_codes-1.2.1.dist-info/RECORD
