Metadata-Version: 2.1
Name: py-polar-codes
Version: 1.2.1
Summary: A package for polar codes in Python.
Home-page: https://github.com/mcba1n/polar-codes
Author: Brendon McBain
Author-email: brendon.mcbain9@gmail.com
License: UNKNOWN
Platform: UNKNOWN
Classifier: Programming Language :: Python :: 3
Classifier: License :: OSI Approved :: MIT License
Classifier: Operating System :: OS Independent
Requires-Python: >=3.6
Requires-Dist: numpy
Requires-Dist: matplotlib
